django_datahooks/__init__.py
django_datahooks/apps.py
django_datahooks/decorators.py
django_datahooks/finder.py
django_datahooks/provider.py
django_datahooks/registry.py
django_datahooks/management/__init__.py
django_datahooks/management/commands/__init__.py
django_datahooks/management/commands/generate_data.py
django_datahooks-0.0.1.dist-info/LICENSE
django_datahooks-0.0.1.dist-info/METADATA
django_datahooks-0.0.1.dist-info/WHEEL
django_datahooks-0.0.1.dist-info/top_level.txt
django_datahooks-0.0.1.dist-info/RECORD
