Metadata-Version: 2.1
Name: django-datahooks
Version: 0.0.1
Summary: Django datahooks
Home-page: https://github.com/labd/django-datahooks
Author: Lab Digital
Author-email: opensource@labdigital.nl
License: MIT
Platform: UNKNOWN
Classifier: Development Status :: 5 - Production/Stable
Classifier: Environment :: Web Environment
Classifier: Framework :: Django
Classifier: Framework :: Django :: 1.11
Classifier: License :: OSI Approved :: MIT License
Classifier: Programming Language :: Python
Classifier: Programming Language :: Python :: 3
Classifier: Programming Language :: Python :: 3.6
Requires-Dist: Django (>=1.11)
Provides-Extra: docs
Requires-Dist: mkdocs (>=1.0.4) ; extra == 'docs'
Requires-Dist: mkdocs-material (==4.4.0) ; extra == 'docs'
Provides-Extra: test
Requires-Dist: coverage (==4.5.3) ; extra == 'test'
Requires-Dist: pytest (==5.0.1) ; extra == 'test'
Requires-Dist: pytest-django (==3.5.1) ; extra == 'test'
Requires-Dist: isort (==4.2.5) ; extra == 'test'
Requires-Dist: flake8 (==3.7.7) ; extra == 'test'
Requires-Dist: flake8-blind-except (==0.1.1) ; extra == 'test'
Requires-Dist: flake8-debugger (==1.4.0) ; extra == 'test'
